cloud_ops/server.py
mcp_cloud_ops-0.1.1.dist-info/METADATA
mcp_cloud_ops-0.1.1.dist-info/WHEEL
mcp_cloud_ops-0.1.1.dist-info/entry_points.txt
mcp_cloud_ops-0.1.1.dist-info/licenses/LICENSE
mcp_cloud_ops-0.1.1.dist-info/RECORD
